prepipy/__init__.py
prepipy/auxiliaries.py
prepipy/config/config_comments.yml
prepipy/config/logging_config.yml
prepipy/config/masking_example.yml
prepipy/config_file_examples/bands.yml
prepipy/config_file_examples/config_single.yml
prepipy/config_file_examples/mask.yml
prepipy/configuration.py
prepipy/framework.py
prepipy/framework_sources.py
prepipy/masking.py
prepipy/resources/grey_values.yml
prepipy/resources/html_templates.yml
prepipy/resources/stiff_params.yml
prepipy/rgbcombo.py
prepipy-0.7.0.dist-info/LICENSE
prepipy-0.7.0.dist-info/METADATA
prepipy-0.7.0.dist-info/WHEEL
prepipy-0.7.0.dist-info/entry_points.txt
prepipy-0.7.0.dist-info/RECORD
