Metadata-Version: 2.1
Name: prepipy
Version: 0.7.0
Summary: Provides the ability to stretch and combine astronomical images from multiple bands into (RGB) colour images.
Home-page: https://github.com/teutoburg/prepipy
License: GPL-3.0-or-later
Author: Fabian Haberhauer
Author-email: fabian.haberhauer@univie.ac.at
Maintainer: teutoburg
Maintainer-email: ghost@instruct.at
Requires-Python: >=3.9,<4.0
Classifier: Intended Audience :: Science/Research
Classifier: License :: OSI Approved :: GNU General Public License v3 or later (GPLv3+)
Classifier: Operating System :: OS Independent
Classifier: Programming Language :: Python :: 3
Classifier: Programming Language :: Python :: 3.9
Classifier: Programming Language :: Python :: 3.10
Classifier: Programming Language :: Python :: 3.11
Classifier: Programming Language :: Python :: 3.12
Classifier: Topic :: Scientific/Engineering :: Astronomy
Classifier: Topic :: Scientific/Engineering :: Image Processing
Classifier: Topic :: Scientific/Engineering :: Visualization
Classifier: Typing :: Typed
Requires-Dist: Pillow (>=10.0.1,<11.0.0)
Requires-Dist: astropy (>=5.3.4,<6.0.0)
Requires-Dist: colorama (>=0.4.6,<0.5.0)
Requires-Dist: matplotlib (>=3.8,<4.0)
Requires-Dist: numpy (>=1.24.4,<2.0.0)
Requires-Dist: regions (>=0.8,<0.9)
Requires-Dist: ruamel.yaml (>=0.17.21,<0.18.0)
Requires-Dist: tqdm (>=4.66.1,<5.0.0)
Project-URL: Repository, https://github.com/teutoburg/prepipy
